serialcables_sphinx/__init__.py
serialcables_sphinx/cli.py
serialcables_sphinx/profiler_cli.py
serialcables_sphinx/shortcuts.py
serialcables_sphinx/shortcuts_cli.py
serialcables_sphinx/sphinx.py
serialcables_sphinx/mctp/__init__.py
serialcables_sphinx/mctp/builder.py
serialcables_sphinx/mctp/constants.py
serialcables_sphinx/mctp/fragmentation.py
serialcables_sphinx/mctp/header.py
serialcables_sphinx/mctp/parser.py
serialcables_sphinx/nvme_mi/__init__.py
serialcables_sphinx/nvme_mi/admin_tunneling.py
serialcables_sphinx/nvme_mi/base_decoder.py
serialcables_sphinx/nvme_mi/capsule.py
serialcables_sphinx/nvme_mi/client.py
serialcables_sphinx/nvme_mi/constants.py
serialcables_sphinx/nvme_mi/decoder.py
serialcables_sphinx/nvme_mi/decoders.py
serialcables_sphinx/nvme_mi/opcodes.py
serialcables_sphinx/nvme_mi/registry.py
serialcables_sphinx/nvme_mi/request.py
serialcables_sphinx/nvme_mi/response.py
serialcables_sphinx/nvme_mi/status.py
serialcables_sphinx/nvme_mi/version.py
serialcables_sphinx/profiler/__init__.py
serialcables_sphinx/profiler/capture.py
serialcables_sphinx/profiler/loader.py
serialcables_sphinx/profiler/profile.py
serialcables_sphinx/transports/__init__.py
serialcables_sphinx/transports/base.py
serialcables_sphinx/transports/hydra.py
serialcables_sphinx/transports/mock.py
serialcables_sphinx/utils/__init__.py
serialcables_sphinx/utils/formatting.py
serialcables_sphinx-0.6.1.dist-info/licenses/LICENSE
serialcables_sphinx-0.6.1.dist-info/METADATA
serialcables_sphinx-0.6.1.dist-info/WHEEL
serialcables_sphinx-0.6.1.dist-info/entry_points.txt
serialcables_sphinx-0.6.1.dist-info/top_level.txt
serialcables_sphinx-0.6.1.dist-info/RECORD
