Metadata-Version: 2.4
Name: serialcables-sphinx
Version: 0.6.1
Summary: MCTP and NVMe-MI protocol library for Serial Cables hardware
Author: Serial Cables, LLC
License-Expression: MIT
Project-URL: Homepage, https://github.com/serialcables/serialcables-sphinx
Project-URL: Documentation, https://serialcables-sphinx.readthedocs.io
Project-URL: Repository, https://github.com/serialcables/serialcables-sphinx
Project-URL: Issues, https://github.com/serialcables/serialcables-sphinx/issues
Keywords: nvme,nvme-mi,mctp,pcie,storage,ssd,management,smbus,i2c,i3c,compliance,testing,unh-iol
Classifier: Development Status :: 3 - Alpha
Classifier: Intended Audience :: Developers
Classifier: Intended Audience :: Manufacturing
Classifier: Operating System :: OS Independent
Classifier: Programming Language :: Python :: 3
Classifier: Programming Language :: Python :: 3.9
Classifier: Programming Language :: Python :: 3.10
Classifier: Programming Language :: Python :: 3.11
Classifier: Programming Language :: Python :: 3.12
Classifier: Topic :: System :: Hardware
Classifier: Topic :: System :: Hardware :: Hardware Drivers
Classifier: Topic :: Software Development :: Libraries :: Python Modules
Classifier: Topic :: Software Development :: Testing
Requires-Python: >=3.9
License-File: LICENSE
Requires-Dist: serialcables-hydra>=1.3.0
Provides-Extra: dev
Requires-Dist: pytest>=7.0; extra == "dev"
Requires-Dist: pytest-cov>=4.0; extra == "dev"
Requires-Dist: black>=23.0; extra == "dev"
Requires-Dist: ruff>=0.1.0; extra == "dev"
Requires-Dist: mypy>=1.0; extra == "dev"
Provides-Extra: docs
Requires-Dist: sphinx>=7.0; extra == "docs"
Requires-Dist: sphinx-rtd-theme>=2.0; extra == "docs"
Dynamic: license-file
